iServTools/__init__.py
iServTools/__main__.py
iServTools/iservData.py
iServTools/iservGroups.py
iServTools/iservImport.py
iServTools/iservProWo.py
iServTools/iservTools.py
iservTools-0.0.14.dist-info/LICENSE
iservTools-0.0.14.dist-info/METADATA
iservTools-0.0.14.dist-info/WHEEL
iservTools-0.0.14.dist-info/top_level.txt
iservTools-0.0.14.dist-info/RECORD
