Metadata-Version: 2.1
Name: iservTools
Version: 0.0.14
Summary: Tools for iServ school servers
Home-page: UNKNOWN
Author: Christian Eckhardt
Author-email: Christian.Eckhardt@gmx.de
License: MIT
Platform: UNKNOWN
Classifier: License :: OSI Approved :: MIT License
Classifier: Programming Language :: Python :: 3
Classifier: Programming Language :: Python :: 3.7
Requires-Dist: selenium
Requires-Dist: openpyxl
